luxa/__init__.py
luxa-0.1.0.dist-info/METADATA
luxa-0.1.0.dist-info/WHEEL
luxa-0.1.0.dist-info/top_level.txt
luxa-0.1.0.dist-info/RECORD
