Metadata-Version: 2.1
Name: luxa
Version: 0.1.0
Summary: Fast build system for jailbreak tweaks
Home-page: UNKNOWN
Author: Madeline Göttlicher
License: UNKNOWN
Platform: UNKNOWN
